top.sv
module top #(
    parameter CLK_HZ = 12_000_000,
    parameter INTERVAL = CLK_HZ / 6
) (
    input logic clk,
    output logic RGB_R,
    output logic RGB_G,
    output logic RGB_B
);
    logic [$clog2(INTERVAL) - 1:0] count = 0;
    logic tick;
    logic [2:0] step = 0;
    
    assign tick = (count == INTERVAL - 1);
    always_ff @(posedge clk) begin
        if(tick)
            count <= 0;
        else
            count <= count + 1;
    end

    logic r_led_on = 1'b0;
    logic g_led_on = 1'b0;
    logic b_led_on = 1'b0;

    always_ff @(posedge clk) begin
        if (tick)
            if (step == 3'd5) begin
                step <= 3'd0;
            end else begin
                step <= step + 1;
            end
    end

    logic r, g, b;
    always_comb begin
        case (step)
            3'd0: {r, g, b} = 3'b100;
            3'd1: {r, g, b} = 3'b110;
            3'd2: {r, g, b} = 3'b010;
            3'd3: {r, g, b} = 3'b011;
            3'd4: {r, g, b} = 3'b001;
            3'd5: {r, g, b} = 3'b101;
            default: {r, g, b} = 3'b000;
        endcase
    end

    assign RGB_R = ~r;
    assign RGB_G = ~g;
    assign RGB_B = ~b;

endmodule

top_tb.sv
`timescale 1ns/1ps
`include "top.sv"

module top_tb;
    logic clk = 0;
    logic RGB_R;
    logic RGB_G;
    logic RGB_B;

    top #(.CLK_HZ(20)) dut (
        .clk (clk),
        .RGB_R (RGB_R),
        .RGB_G (RGB_G),
        .RGB_B (RGB_B)
    );

    always #41.667 clk = ~clk;

    initial begin
        $dumpfile("top.vcd");
        $dumpvars(0, top_tb);
        #5000;
        $finish;
    end

endmodule

build/top.vcd
$date
	Fri Sep 18 13:51:13 2026
$end
$version
	Icarus Verilog
$end
$timescale
	1ps
$end
$scope module top_tb $end
$var wire 1 ! RGB_R $end
$var wire 1 " RGB_G $end
$var wire 1 # RGB_B $end
$var reg 1 $ clk $end
$scope module dut $end
$var wire 1 # RGB_B $end
$var wire 1 " RGB_G $end
$var wire 1 ! RGB_R $end
$var wire 1 $ clk $end
$var wire 1 % tick $end
$var parameter 32 & CLK_HZ $end
$var parameter 32 ' INTERVAL $end
$var reg 1 ( b $end
$var reg 1 ) b_led_on $end
$var reg 2 * count [1:0] $end
$var reg 1 + g $end
$var reg 1 , g_led_on $end
$var reg 1 - r $end
$var reg 1 . r_led_on $end
$var reg 3 / step [2:0] $end
$upscope $end
$upscope $end
$enddefinitions $end
$comment Show the parameter values. $end
$dumpall
b11 '
b10100 &
$end
#0
$dumpvars
b0 /
0.
1-
0,
0+
b0 *
0)
0(
0%
0$
1#
1"
0!
$end
#41667
b1 *
1$
#83334
0$
#125001
1%
b10 *
1$
#166668
0$
#208335
0"
0%
1+
b0 *
b1 /
1$
#250002
0$
#291669
b1 *
1$
#333336
0$
#375003
1%
b10 *
1$
#416670
0$
#458337
1!
0-
0%
b10 /
b0 *
1$
#500004
0$
#541671
b1 *
1$
#583338
0$
#625005
1%
b10 *
1$
#666672
0$
#708339
0#
0%
1(
b0 *
b11 /
1$
#750006
0$
#791673
b1 *
1$
#833340
0$
#875007
1%
b10 *
1$
#916674
0$
#958341
1"
0+
0%
b100 /
b0 *
1$
#1000008
0$
#1041675
b1 *
1$
#1083342
0$
#1125009
1%
b10 *
1$
#1166676
0$
#1208343
0!
0%
1-
b0 *
b101 /
1$
#1250010
0$
#1291677
b1 *
1$
#1333344
0$
#1375011
1%
b10 *
1$
#1416678
0$
#1458345
1#
0(
0%
b0 /
b0 *
1$
#1500012
0$
#1541679
b1 *
1$
#1583346
0$
#1625013
1%
b10 *
1$
#1666680
0$
#1708347
0"
0%
1+
b0 *
b1 /
1$
#1750014
0$
#1791681
b1 *
1$
#1833348
0$
#1875015
1%
b10 *
1$
#1916682
0$
#1958349
1!
0-
0%
b10 /
b0 *
1$
#2000016
0$
#2041683
b1 *
1$
#2083350
0$
#2125017
1%
b10 *
1$
#2166684
0$
#2208351
0#
0%
1(
b0 *
b11 /
1$
#2250018
0$
#2291685
b1 *
1$
#2333352
0$
#2375019
1%
b10 *
1$
#2416686
0$
#2458353
1"
0+
0%
b100 /
b0 *
1$
#2500020
0$
#2541687
b1 *
1$
#2583354
0$
#2625021
1%
b10 *
1$
#2666688
0$
#2708355
0!
0%
1-
b0 *
b101 /
1$
#2750022
0$
#2791689
b1 *
1$
#2833356
0$
#2875023
1%
b10 *
1$
#2916690
0$
#2958357
1#
0(
0%
b0 /
b0 *
1$
#3000024
0$
#3041691
b1 *
1$
#3083358
0$
#3125025
1%
b10 *
1$
#3166692
0$
#3208359
0"
0%
1+
b0 *
b1 /
1$
#3250026
0$
#3291693
b1 *
1$
#3333360
0$
#3375027
1%
b10 *
1$
#3416694
0$
#3458361
1!
0-
0%
b10 /
b0 *
1$
#3500028
0$
#3541695
b1 *
1$
#3583362
0$
#3625029
1%
b10 *
1$
#3666696
0$
#3708363
0#
0%
1(
b0 *
b11 /
1$
#3750030
0$
#3791697
b1 *
1$
#3833364
0$
#3875031
1%
b10 *
1$
#3916698
0$
#3958365
1"
0+
0%
b100 /
b0 *
1$
#4000032
0$
#4041699
b1 *
1$
#4083366
0$
#4125033
1%
b10 *
1$
#4166700
0$
#4208367
0!
0%
1-
b0 *
b101 /
1$
#4250034
0$
#4291701
b1 *
1$
#4333368
0$
#4375035
1%
b10 *
1$
#4416702
0$
#4458369
1#
0(
0%
b0 /
b0 *
1$
#4500036
0$
#4541703
b1 *
1$
#4583370
0$
#4625037
1%
b10 *
1$
#4666704
0$
#4708371
0"
0%
1+
b0 *
b1 /
1$
#4750038
0$
#4791705
b1 *
1$
#4833372
0$
#4875039
1%
b10 *
1$
#4916706
0$
#4958373
1!
0-
0%
b10 /
b0 *
1$
